NklResponse.py
NklTarget.py
constantes.py
nakalapycon.py
nklAPI_Collections.py
nklAPI_Datas.py
nklAPI_Groups.py
nklAPI_Search.py
nklAPI_Users.py
nklAPI_Vocabularies.py
nklPullCorpus.py
nklUtils.py
nakalapycon-0.0.9.dist-info/LICENSE
nakalapycon-0.0.9.dist-info/METADATA
nakalapycon-0.0.9.dist-info/WHEEL
nakalapycon-0.0.9.dist-info/top_level.txt
nakalapycon-0.0.9.dist-info/RECORD
