Metadata-Version: 2.1
Name: nakalapycon
Version: 0.0.9
Summary: Librairie Python pour interagir avec Nakala (Nakala est un entrepôt de données de recherche en SHS développé par Huma-Num)
Home-page: https://gitlab.huma-num.fr/mshs-poitiers/plateforme/nakalapycon
Author: Michael Nauge
Project-URL: Issues, https://gitlab.huma-num.fr/mshs-poitiers/plateforme/nakalapycon/-/issues
Project-URL: CI, https://gitlab.huma-num.fr/mshs-poitiers/plateforme/nakalapycon/-/pipelines
Project-URL: Changelog, https://gitlab.huma-num.fr/mshs-poitiers/plateforme/nakalapycon/-/blob/master/CHANGELOG.md
Classifier: Programming Language :: Python :: 3
Classifier: License :: OSI Approved :: GNU General Public License (GPL)
Classifier: Operating System :: OS Independent
Requires-Python: >=3.6
License-File: LICENSE
Requires-Dist: requests
Requires-Dist: pandas
